pump_flash.py
setup.py
pump_flash.egg-info/PKG-INFO
pump_flash.egg-info/SOURCES.txt
pump_flash.egg-info/dependency_links.txt
pump_flash.egg-info/top_level.txt