Metadata-Version: 1.0
Name: pump-flash
Version: 0.0.1
Summary: A Pump middleware for adding flash message support via sessions.
Home-page: UNKNOWN
Author: Adeel Ahmad Khan
Author-email: adeel@adeel.ru
License: MIT
Platform: UNKNOWN
